qlknn/NNDB/__init__.py
qlknn/NNDB/extract_nns.py
qlknn/NNDB/get_best.py
qlknn/NNDB/model.py
qlknn/NNDB/postprocess.py
qlknn/NNDB/stats.py
qlknn/__init__.py
qlknn/cli.py
qlknn/dataset/__init__.py
qlknn/dataset/calculate_instance_weights.py
qlknn/dataset/clustering.py
qlknn/dataset/data_io.py
qlknn/dataset/filter_archive/edgerun_eight.py
qlknn/dataset/filter_archive/edgerun_eight_glueing.py
qlknn/dataset/filter_archive/edgerun_eight_output_statistics.py
qlknn/dataset/filter_archive/edgerun_seven.py
qlknn/dataset/filter_archive/edgerun_six.py
qlknn/dataset/filter_archive/edgerun_ten.py
qlknn/dataset/filter_archive/megarun_one_filter.py
qlknn/dataset/filter_archive/megarun_one_to_pandas.py
qlknn/dataset/filter_datasets.py
qlknn/dataset/filtering.py
qlknn/dataset/hypercube_to_pandas.py
qlknn/dataset/mapping.py
qlknn/dataset/prep_datasets.py
qlknn/dataset/separate7D.py
qlknn/gui/__init__.py
qlknn/gui/slice_gui.py
qlknn/misc/__init__.py
qlknn/misc/activation_showcase.py
qlknn/misc/analyse_names.py
qlknn/misc/binning.py
qlknn/misc/dataset_measure_mem.sh
qlknn/misc/dataset_memtest.py
qlknn/misc/dataset_snippits.py
qlknn/misc/dataset_storage_format_profiler.py
qlknn/misc/get_dataset_standardization.py
qlknn/misc/random_access_benchmark.py
qlknn/misc/to_precision.py
qlknn/misc/tools.py
qlknn/models/__init__.py
qlknn/models/clipping.py
qlknn/models/committee.py
qlknn/models/cython_mkl_ndnn.py
qlknn/models/ffnn.py
qlknn/models/kerasmodel.py
qlknn/models/qlknn_fortran.py
qlknn/models/qlknn_hyper_10D.py
qlknn/models/qlknnmodule.c
qlknn/models/rotdiv.py
qlknn/models/setup.py
qlknn/models/victor_rule.py
qlknn/pipeline/__init__.py
qlknn/pipeline/luigi.cfg
qlknn/pipeline/one_off_tasks.py
qlknn/pipeline/pipeline.py
qlknn/pipeline/simple_scanner.py
qlknn/pipeline/train_NDNN_cori_haswell.sh
qlknn/pipeline/train_NDNN_lisa.sh
qlknn/pipeline/train_NDNN_marconi.sh
qlknn/pipeline/train_launch.py
qlknn/plots/.gitignore
qlknn/plots/HornNet_slice.py
qlknn/plots/__init__.py
qlknn-1.3.1.dist-info/LICENSE
qlknn-1.3.1.dist-info/METADATA
qlknn-1.3.1.dist-info/WHEEL
qlknn-1.3.1.dist-info/entry_points.txt
qlknn-1.3.1.dist-info/RECORD
